layerzero/__init__.py
layerzero/exceptions.py
layerzero/mainnet.py
layerzero/testnet.py
layerzero/enums/__init__.py
layerzero/enums/endpoints_enum.py
layerzero/enums/operations_enum.py
layerzero/enums/queries_enum.py
layerzero/types/__init__.py
layerzero/types/json_deserializable.py
layerzero/types/types.py
layerzero/wrappers/__init__.py
layerzero/wrappers/test_wrapper.py
layerzero/wrappers/wrapper.py
layerzero_scan-1.0.0.dist-info/LICENSE
layerzero_scan-1.0.0.dist-info/METADATA
layerzero_scan-1.0.0.dist-info/WHEEL
layerzero_scan-1.0.0.dist-info/top_level.txt
layerzero_scan-1.0.0.dist-info/RECORD
