Metadata-Version: 2.1
Name: layerzero-scan
Version: 1.0.0
Summary: A minimal Python API for LayerZero Scan
Home-page: https://github.com/kamilgg/layerzero-scan
Author: Kamil Gatin
Author-email: kamil.gatin2604@gmail.com
License: MIT
License-File: LICENSE
Requires-Dist: requests
Requires-Dist: pytest
